gbm/__init__.py
gbm/data.py
gbm/loc.py
gbm/signal.py
gbm-0.0.1.dist-info/METADATA
gbm-0.0.1.dist-info/RECORD
gbm-0.0.1.dist-info/WHEEL
gbm-0.0.1.dist-info/top_level.txt
