Metadata-Version: 2.1
Name: gbm
Version: 0.0.1
Summary: Read and analyze GBM data
Home-page: https://github.com/ahnitz/gbm
Author: Alexander Harvey Nitz
Author-email: alex.nitz@gmail.com
License: UNKNOWN
Platform: UNKNOWN
Classifier: Programming Language :: Python :: 2.7
Classifier: License :: OSI Approved :: GNU General Public License v3 (GPLv3)
Classifier: Operating System :: OS Independent
Classifier: Intended Audience :: Science/Research
Classifier: Natural Language :: English
Requires-Dist: numpy
Requires-Dist: astropy
